{
  "version": "181",
  "builtAt": "2026-04-03T06:00:45.692Z",
  "note": "Exact V180.1 revenue drives promote/demote; inferred-only paths excluded from max priority.",
  "top_revenue_tools_exact": [],
  "top_revenue_pages_exact": [],
  "top_revenue_topics_exact": [],
  "low_revenue_high_traffic_topics": [
    {
      "topic": "travel",
      "path": "/blog/tiktok-captions-travel",
      "page_value_proxy": 0.712,
      "action": "demote_allocation"
    },
    {
      "topic": "trending-ideas",
      "path": "/blog/youtube-captions-trending-ideas",
      "page_value_proxy": 0.712,
      "action": "demote_allocation"
    },
    {
      "topic": "motivation",
      "path": "/blog/tiktok-captions-motivation",
      "page_value_proxy": 0.711,
      "action": "demote_allocation"
    },
    {
      "topic": "food",
      "path": "/blog/tiktok-captions-food",
      "page_value_proxy": 0.71,
      "action": "demote_allocation"
    },
    {
      "topic": "life-hack",
      "path": "/blog/tiktok-captions-life-hack",
      "page_value_proxy": 0.71,
      "action": "demote_allocation"
    },
    {
      "topic": "funny-usernames",
      "path": "/blog/instagram-hashtags-funny-usernames",
      "page_value_proxy": 0.709,
      "action": "demote_allocation"
    },
    {
      "topic": "inspirational",
      "path": "/blog/tiktok-captions-inspirational",
      "page_value_proxy": 0.709,
      "action": "demote_allocation"
    },
    {
      "topic": "romantic",
      "path": "/blog/tiktok-captions-romantic",
      "page_value_proxy": 0.709,
      "action": "demote_allocation"
    },
    {
      "topic": "for-reels",
      "path": "/blog/instagram-captions-for-reels",
      "page_value_proxy": 0.708,
      "action": "demote_allocation"
    },
    {
      "topic": "attitude",
      "path": "/blog/tiktok-captions-attitude",
      "page_value_proxy": 0.708,
      "action": "demote_allocation"
    },
    {
      "topic": "cute",
      "path": "/blog/tiktok-captions-cute",
      "page_value_proxy": 0.708,
      "action": "demote_allocation"
    },
    {
      "topic": "grwm",
      "path": "/blog/instagram-captions-grwm",
      "page_value_proxy": 0.707,
      "action": "demote_allocation"
    },
    {
      "topic": "script-structure",
      "path": "/blog/instagram-captions-script-structure",
      "page_value_proxy": 0.707,
      "action": "demote_allocation"
    },
    {
      "topic": "tips",
      "path": "/blog/instagram-hooks-tips",
      "page_value_proxy": 0.707,
      "action": "demote_allocation"
    },
    {
      "topic": "trending-sound",
      "path": "/blog/instagram-hooks-trending-sound",
      "page_value_proxy": 0.707,
      "action": "demote_allocation"
    },
    {
      "topic": "viral-hashtags",
      "path": "/blog/instagram-hooks-viral-hashtags",
      "page_value_proxy": 0.707,
      "action": "demote_allocation"
    },
    {
      "topic": "friends",
      "path": "/blog/tiktok-captions-friends",
      "page_value_proxy": 0.707,
      "action": "demote_allocation"
    },
    {
      "topic": "gaming",
      "path": "/blog/tiktok-captions-gaming",
      "page_value_proxy": 0.707,
      "action": "demote_allocation"
    },
    {
      "topic": "sarcastic",
      "path": "/blog/tiktok-captions-sarcastic",
      "page_value_proxy": 0.707,
      "action": "demote_allocation"
    },
    {
      "topic": "caption-for-business",
      "path": "/blog/tiktok-hooks-caption-for-business",
      "page_value_proxy": 0.707,
      "action": "demote_allocation"
    },
    {
      "topic": "stitch",
      "path": "/blog/youtube-captions-stitch",
      "page_value_proxy": 0.707,
      "action": "demote_allocation"
    },
    {
      "topic": "grwm",
      "path": "/blog/youtube-hashtags-grwm",
      "page_value_proxy": 0.707,
      "action": "demote_allocation"
    },
    {
      "topic": "duet-ideas",
      "path": "/blog/instagram-hashtags-duet-ideas",
      "page_value_proxy": 0.706,
      "action": "demote_allocation"
    },
    {
      "topic": "prank",
      "path": "/blog/instagram-hashtags-prank",
      "page_value_proxy": 0.706,
      "action": "demote_allocation"
    },
    {
      "topic": "ootd",
      "path": "/blog/instagram-hooks-ootd",
      "page_value_proxy": 0.706,
      "action": "demote_allocation"
    },
    {
      "topic": "comedy-ideas",
      "path": "/blog/instagram-titles-comedy-ideas",
      "page_value_proxy": 0.706,
      "action": "demote_allocation"
    },
    {
      "topic": "collab",
      "path": "/blog/tiktok-captions-collab",
      "page_value_proxy": 0.706,
      "action": "demote_allocation"
    },
    {
      "topic": "funny",
      "path": "/blog/tiktok-captions-funny",
      "page_value_proxy": 0.706,
      "action": "demote_allocation"
    },
    {
      "topic": "hook-examples",
      "path": "/blog/tiktok-hashtags-hook-examples",
      "page_value_proxy": 0.706,
      "action": "demote_allocation"
    },
    {
      "topic": "long",
      "path": "/blog/tiktok-hashtags-long",
      "page_value_proxy": 0.706,
      "action": "demote_allocation"
    },
    {
      "topic": "selfie",
      "path": "/blog/tiktok-hashtags-selfie",
      "page_value_proxy": 0.706,
      "action": "demote_allocation"
    },
    {
      "topic": "niche-hashtags",
      "path": "/blog/tiktok-hooks-niche-hashtags",
      "page_value_proxy": 0.706,
      "action": "demote_allocation"
    },
    {
      "topic": "comedy-reel",
      "path": "/blog/youtube-captions-comedy-reel",
      "page_value_proxy": 0.706,
      "action": "demote_allocation"
    },
    {
      "topic": "comedy-hashtags",
      "path": "/blog/youtube-hooks-comedy-hashtags",
      "page_value_proxy": 0.706,
      "action": "demote_allocation"
    },
    {
      "topic": "food-ideas",
      "path": "/blog/youtube-hooks-food-ideas",
      "page_value_proxy": 0.706,
      "action": "demote_allocation"
    },
    {
      "topic": "caption-for-business",
      "path": "/blog/youtube-titles-caption-for-business",
      "page_value_proxy": 0.706,
      "action": "demote_allocation"
    },
    {
      "topic": "get-ready-with-me",
      "path": "/blog/youtube-titles-get-ready-with-me",
      "page_value_proxy": 0.706,
      "action": "demote_allocation"
    },
    {
      "topic": "for-business",
      "path": "/blog/instagram-captions-for-business",
      "page_value_proxy": 0.705,
      "action": "demote_allocation"
    },
    {
      "topic": "mystery",
      "path": "/blog/instagram-hooks-mystery",
      "page_value_proxy": 0.705,
      "action": "demote_allocation"
    },
    {
      "topic": "caption-ideas",
      "path": "/blog/instagram-titles-caption-ideas",
      "page_value_proxy": 0.705,
      "action": "demote_allocation"
    },
    {
      "topic": "gym",
      "path": "/blog/tiktok-captions-gym",
      "page_value_proxy": 0.705,
      "action": "demote_allocation"
    },
    {
      "topic": "trending-sounds-ideas",
      "path": "/blog/tiktok-titles-trending-sounds-ideas",
      "page_value_proxy": 0.705,
      "action": "demote_allocation"
    },
    {
      "topic": "get-ready-with-me",
      "path": "/blog/youtube-captions-get-ready-with-me",
      "page_value_proxy": 0.705,
      "action": "demote_allocation"
    },
    {
      "topic": "relatable",
      "path": "/blog/youtube-hashtags-relatable",
      "page_value_proxy": 0.705,
      "action": "demote_allocation"
    },
    {
      "topic": "script",
      "path": "/blog/youtube-hashtags-script",
      "page_value_proxy": 0.705,
      "action": "demote_allocation"
    },
    {
      "topic": "dance",
      "path": "/blog/youtube-titles-dance",
      "page_value_proxy": 0.705,
      "action": "demote_allocation"
    },
    {
      "topic": "lets-play",
      "path": "/blog/instagram-hooks-lets-play",
      "page_value_proxy": 0.704,
      "action": "demote_allocation"
    },
    {
      "topic": "aesthetic",
      "path": "/blog/tiktok-captions-aesthetic",
      "page_value_proxy": 0.704,
      "action": "demote_allocation"
    },
    {
      "topic": "comedy",
      "path": "/blog/tiktok-captions-comedy",
      "page_value_proxy": 0.704,
      "action": "demote_allocation"
    },
    {
      "topic": "cover",
      "path": "/blog/tiktok-captions-cover",
      "page_value_proxy": 0.704,
      "action": "demote_allocation"
    },
    {
      "topic": "how-to",
      "path": "/blog/tiktok-captions-how-to",
      "page_value_proxy": 0.704,
      "action": "demote_allocation"
    },
    {
      "topic": "promotion",
      "path": "/blog/tiktok-captions-promotion",
      "page_value_proxy": 0.704,
      "action": "demote_allocation"
    },
    {
      "topic": "sad",
      "path": "/blog/tiktok-captions-sad",
      "page_value_proxy": 0.704,
      "action": "demote_allocation"
    },
    {
      "topic": "attitude",
      "path": "/blog/tiktok-hashtags-attitude",
      "page_value_proxy": 0.704,
      "action": "demote_allocation"
    },
    {
      "topic": "wedding",
      "path": "/blog/tiktok-hooks-wedding",
      "page_value_proxy": 0.704,
      "action": "demote_allocation"
    },
    {
      "topic": "product",
      "path": "/blog/tiktok-titles-product",
      "page_value_proxy": 0.704,
      "action": "demote_allocation"
    },
    {
      "topic": "contest",
      "path": "/blog/youtube-hooks-contest",
      "page_value_proxy": 0.704,
      "action": "demote_allocation"
    },
    {
      "topic": "dad",
      "path": "/blog/youtube-hooks-dad",
      "page_value_proxy": 0.704,
      "action": "demote_allocation"
    },
    {
      "topic": "wedding",
      "path": "/blog/youtube-hooks-wedding",
      "page_value_proxy": 0.704,
      "action": "demote_allocation"
    },
    {
      "topic": "ideas-for-beginners",
      "path": "/blog/youtube-titles-ideas-for-beginners",
      "page_value_proxy": 0.704,
      "action": "demote_allocation"
    }
  ],
  "revenue_demote_topics": [
    "for-reels",
    "bio-ideas",
    "asmr",
    "business",
    "comparison",
    "creative-usernames",
    "duet",
    "for-business",
    "for-selfies",
    "grwm",
    "niche",
    "ootd",
    "romantic",
    "script-structure",
    "challenge",
    "cottagecore",
    "duet-ideas",
    "fitness",
    "funny-usernames",
    "gaming-ideas",
    "prank",
    "story",
    "storytime",
    "sunset",
    "challenge-ideas",
    "comedy-reel",
    "content-ideas",
    "fitness-ideas",
    "lets-play",
    "mom-life",
    "mystery",
    "tips",
    "title-for-views",
    "trending-sound",
    "tutorial",
    "viral-hashtags",
    "aesthetic",
    "best-hashtags",
    "caption-ideas",
    "comedy-hashtags",
    "comedy-ideas",
    "food-ideas",
    "love",
    "minimalist",
    "savage",
    "small-business",
    "transformation",
    "advanced",
    "adventure",
    "aesthetic-reel",
    "attitude",
    "baddie",
    "beauty-hashtags",
    "before-after",
    "beginners",
    "behind-the-scenes",
    "best",
    "clean-girl",
    "clickbait",
    "coffee",
    "collab",
    "comedy",
    "confidence",
    "contest",
    "controversial",
    "cover",
    "curiosity",
    "cute",
    "dad",
    "dance-reel",
    "dance",
    "day-in-my-life",
    "education",
    "engagement",
    "entrepreneur",
    "family",
    "fashion-hashtags",
    "finance",
    "first-line",
    "fitness-hashtags"
  ],
  "revenue_promote_topics": [],
  "revenue_promote_intents": [],
  "intent_revenue_multipliers": {
    "captions": 1,
    "hashtags": 1,
    "titles": 1,
    "hooks": 1
  },
  "topic_revenue_multipliers": {
    "Creator intent: Get more views. Content scenario: Tutorial. Hook/video topic: Un": 1,
    "hello": 1,
    "Creator intent: Get more views. Content scenario: Tutorial. Hook/video topic: Ge": 1,
    "Creator intent: Get more views. Content scenario: Tutorial. Hook/video topic: he": 1,
    "Creator intent: Promote a product. Content scenario: Small business. Hook/video": 1,
    "Creator intent: Get more views. Content scenario: Tutorial. Hook/video topic: or": 1,
    "Creator intent: Get more views. Content scenario: Tutorial. Hook/video topic: [V": 1,
    "Creator intent: Get more views. Content scenario: Tutorial. Hook/video topic: Us": 1,
    "Creator intent: Promote a product. Content scenario: Small business. Topic or pr": 1,
    "Test post about morning coffee routine for TikTok": 1,
    "for-reels": 0.9,
    "bio-ideas": 0.9,
    "bios-2025": 1,
    "captions-for-views": 1,
    "titles-for-views": 1,
    "captions": 1,
    "go-viral-on-tiktok": 1,
    "write-tiktok-hooks": 1,
    "write-viral-hooks": 1,
    "asmr": 0.7290000000000001,
    "business": 0.9,
    "comparison": 0.9,
    "creative-usernames": 0.9,
    "duet": 0.9,
    "for-business": 0.9,
    "for-selfies": 0.9,
    "grwm": 0.7290000000000001,
    "niche": 0.81,
    "ootd": 0.9,
    "romantic": 0.81,
    "script-structure": 0.7290000000000001,
    "ideas-2025": 1,
    "challenge": 0.9,
    "cottagecore": 0.81,
    "duet-ideas": 0.9,
    "fitness": 0.7290000000000001,
    "funny-usernames": 0.9,
    "gaming-ideas": 0.9,
    "prank": 0.81,
    "story": 0.9,
    "storytime": 0.9,
    "sunset": 0.9,
    "challenge-ideas": 0.9,
    "comedy-reel": 0.6561000000000001,
    "content-ideas": 0.9,
    "fitness-ideas": 0.9,
    "lets-play": 0.7290000000000001,
    "mom-life": 0.81,
    "mystery": 0.7290000000000001,
    "sale": 1,
    "tips": 0.7290000000000001,
    "title-for-views": 0.9,
    "trending-sound": 0.9,
    "tutorial": 0.81,
    "viral-hashtags": 0.9,
    "captions-2025": 1,
    "hashtag-strategy": 1,
    "aesthetic": 0.7290000000000001,
    "best-hashtags": 0.9,
    "caption-ideas": 0.81,
    "comedy-hashtags": 0.6561000000000001,
    "comedy-ideas": 0.9,
    "food-ideas": 0.81,
    "love": 0.9,
    "minimalist": 0.9,
    "savage": 0.81,
    "small-business": 0.81,
    "transformation": 0.6561000000000001,
    "vs-baidu-for-creators": 1,
    "search-engines-find-creator-content": 1,
    "volume-without-spam-signals": 1,
    "robots-and-indexing": 1,
    "formulas": 1,
    "ideas": 1,
    "advanced": 0.9,
    "adventure": 0.9,
    "aesthetic-reel": 0.81,
    "attitude": 0.81,
    "baddie": 0.9,
    "beauty-hashtags": 0.9,
    "before-after": 0.81,
    "beginners": 0.9,
    "behind-the-scenes": 0.9,
    "best": 0.9,
    "brand": 1,
    "clean-girl": 0.81,
    "clickbait": 0.9,
    "coffee": 0.9,
    "collab": 0.9,
    "comedy": 0.9,
    "confidence": 0.9,
    "contest": 0.7290000000000001,
    "controversial": 0.81,
    "cooking": 1,
    "cover": 0.9,
    "curiosity": 0.81,
    "cute": 0.7290000000000001,
    "dad": 0.9,
    "dance-reel": 0.81,
    "dance": 0.81,
    "day-in-my-life": 0.9,
    "diy": 1,
    "edgy": 1,
    "education": 0.9,
    "engagement": 0.81,
    "entrepreneur": 0.9,
    "event": 1,
    "family": 0.9,
    "fashion-hashtags": 0.9,
    "finance": 0.9,
    "first-line": 0.81,
    "fitness-hashtags": 0.9,
    "food-hashtags": 1,
    "food": 0.9,
    "friends": 0.9,
    "funny": 0.7290000000000001,
    "gaming-video": 0.9,
    "gaming": 0.9,
    "get-ready-with-me": 0.7290000000000001,
    "giveaway": 0.81,
    "gym": 0.9,
    "hacks": 0.9,
    "hair": 1,
    "how-to": 0.9,
    "ideas-for-beginners": 0.7290000000000001,
    "inspirational": 0.9,
    "launch": 0.9,
    "life-hack": 0.81,
    "lifestyle": 0.81,
    "list": 0.9,
    "long": 0.9,
    "makeup": 0.9,
    "motivation": 0.9,
    "music": 0.9,
    "nature": 1,
    "new-arrival": 0.81,
    "niche-hashtags": 0.81,
    "opening": 0.9,
    "pet": 0.9,
    "pov": 0.9,
    "product": 0.81,
    "productivity": 0.81,
    "promotion": 0.9,
    "question": 0.81,
    "reaction": 0.9,
    "recipe": 1,
    "relatable": 0.7290000000000001,
    "restaurant": 1,
    "review": 0.81,
    "running": 1,
    "sad": 0.9,
    "sarcastic": 0.9,
    "sassy": 0.9,
    "script-template": 1,
    "secret": 0.9,
    "self-love": 0.9,
    "selfie": 0.81,
    "short": 0.9,
    "skincare": 0.81,
    "stitch-ideas": 0.9,
    "stitch": 0.81,
    "study": 0.9,
    "team": 0.9,
    "tech": 0.9,
    "testimonial": 0.9,
    "that-girl": 0.9,
    "top-10": 1,
    "travel-hashtags": 0.9,
    "travel": 0.7290000000000001,
    "trending-ideas": 0.9,
    "trending-reel": 0.81,
    "trending": 0.9,
    "tutorial-reel": 0.81,
    "unboxing": 0.81,
    "vacation": 0.9,
    "views": 1,
    "viral": 0.9,
    "vlog": 0.9,
    "vs": 0.9,
    "walkthrough": 1,
    "wedding": 0.81,
    "work-from-home": 0.9,
    "y2k": 0.9,
    "yoga": 0.9,
    "ideas-beginners": 1,
    "ideas-that-work": 1,
    "hook-examples": 0.9,
    "brand-hashtags": 1,
    "caption-for-business": 0.81,
    "dance-hashtags": 0.9,
    "dance-ideas": 0.81,
    "reel-captions": 0.9,
    "viral-ideas": 1,
    "beauty-ideas": 1,
    "intro-hooks": 1,
    "title-formulas": 1,
    "trending-sounds-ideas": 0.9,
    "hooks": 1,
    "education-ideas": 0.9,
    "aesthetic-usernames": 0.9,
    "script": 0.9,
    "examples": 1,
    "caption-for-selfies": 1,
    "structure": 1,
    "template-beginners": 1,
    "small-business-hashtags": 0.9,
    "storytime-ideas": 0.9
  },
  "inferred_only_paths_excluded_from_max_tier": []
}